[
  {
    "Date": "2025-11-07",
    "Hour": 4,
    "Summary": "Light shower",
    "Temperature": 15,
    "Feels like": 13,
    "Rain - 50%": 0,
    "Rain - 25%": 0,
    "Rain - 10%": 1,
    "Humidity": 69,
    "UV Index": 0,
    "Cloud cover": 75
  },
  {
    "Date": "2025-11-07",
    "Hour": 5,
    "Summary": "Cloudy",
    "Temperature": 15,
    "Feels like": 13,
    "Rain - 50%": 0,
    "Rain - 25%": 0,
    "Rain - 10%": 0,
    "Humidity": 65,
    "UV Index": 0,
    "Cloud cover": 69
  },
  {
    "Date": "2025-11-07",
    "Hour": 6,
    "Summary": "Cloudy",
    "Temperature": 16,
    "Feels like": 13,
    "Rain - 50%": 0,
    "Rain - 25%": 0,
    "Rain - 10%": 0,
    "Humidity": 56,
    "UV Index": 0,
    "Cloud cover": 69
  },
  {
    "Date": "2025-11-07",
    "Hour": 7,
    "Summary": "Cloudy",
    "Temperature": 17,
    "Feels like": 12,
    "Rain - 50%": 0,
    "Rain - 25%": 0,
    "Rain - 10%": 0,
    "Humidity": 54,
    "UV Index": 0,
    "Cloud cover": 69
  },
  {
    "Date": "2025-11-07",
    "Hour": 8,
    "Summary": "Cloudy",
    "Temperature": 18,
    "Feels like": 13,
    "Rain - 50%": 0,
    "Rain - 25%": 0,
    "Rain - 10%": 0,
    "Humidity": 49,
    "UV Index": 1,
    "Cloud cover": 75
  },
  {
    "Date": "2025-11-07",
    "Hour": 9,
    "Summary": "Cloudy",
    "Temperature": 20,
    "Feels like": 14,
    "Rain - 50%": 0,
    "Rain - 25%": 0,
    "Rain - 10%": 0,
    "Humidity": 47,
    "UV Index": 1,
    "Cloud cover": 75
  },
  {
    "Date": "2025-11-07",
    "Hour": 10,
    "Summary": "Cloudy",
    "Temperature": 21,
    "Feels like": 16,
    "Rain - 50%": 0,
    "Rain - 25%": 0,
    "Rain - 10%": 0,
    "Humidity": 46,
    "UV Index": 1,
    "Cloud cover": 75
  },
  {
    "Date": "2025-11-07",
    "Hour": 11,
    "Summary": "Partly cloudy",
    "Temperature": 22,
    "Feels like": 18,
    "Rain - 50%": 0,
    "Rain - 25%": 0,
    "Rain - 10%": 0,
    "Humidity": 45,
    "UV Index": 6,
    "Cloud cover": 62
  },
  {
    "Date": "2025-11-07",
    "Hour": 12,
    "Summary": "Partly cloudy",
    "Temperature": 24,
    "Feels like": 18,
    "Rain - 50%": 0,
    "Rain - 25%": 0,
    "Rain - 10%": 0,
    "Humidity": 39,
    "UV Index": 6,
    "Cloud cover": 62
  },
  {
    "Date": "2025-11-07",
    "Hour": 13,
    "Summary": "Partly cloudy",
    "Temperature": 26,
    "Feels like": 20,
    "Rain - 50%": 0,
    "Rain - 25%": 0,
    "Rain - 10%": 0,
    "Humidity": 33,
    "UV Index": 6,
    "Cloud cover": 62
  },
  {
    "Date": "2025-11-07",
    "Hour": 14,
    "Summary": "Partly cloudy",
    "Temperature": 28,
    "Feels like": 22,
    "Rain - 50%": 0,
    "Rain - 25%": 0,
    "Rain - 10%": 0,
    "Humidity": 30,
    "UV Index": 7,
    "Cloud cover": 62
  },
  {
    "Date": "2025-11-07",
    "Hour": 15,
    "Summary": "Partly cloudy",
    "Temperature": 29,
    "Feels like": 24,
    "Rain - 50%": 0,
    "Rain - 25%": 0,
    "Rain - 10%": 0,
    "Humidity": 31,
    "UV Index": 7,
    "Cloud cover": 62
  },
  {
    "Date": "2025-11-07",
    "Hour": 16,
    "Summary": "Partly cloudy",
    "Temperature": 29,
    "Feels like": 25,
    "Rain - 50%": 0,
    "Rain - 25%": 0,
    "Rain - 10%": 0,
    "Humidity": 32,
    "UV Index": 7,
    "Cloud cover": 62
  },
  {
    "Date": "2025-11-07",
    "Hour": 17,
    "Summary": "Shower",
    "Temperature": 28,
    "Feels like": 26,
    "Rain - 50%": 0,
    "Rain - 25%": 0,
    "Rain - 10%": 1,
    "Humidity": 35,
    "UV Index": 2,
    "Cloud cover": 73
  },
  {
    "Date": "2025-11-07",
    "Hour": 18,
    "Summary": "Shower",
    "Temperature": 25,
    "Feels like": 22,
    "Rain - 50%": 0,
    "Rain - 25%": 0,
    "Rain - 10%": 1,
    "Humidity": 41,
    "UV Index": 2,
    "Cloud cover": 73
  },
  {
    "Date": "2025-11-07",
    "Hour": 19,
    "Summary": "Shower",
    "Temperature": 22,
    "Feels like": 19,
    "Rain - 50%": 0,
    "Rain - 25%": 0,
    "Rain - 10%": 1,
    "Humidity": 52,
    "UV Index": 2,
    "Cloud cover": 73
  },
  {
    "Date": "2025-11-07",
    "Hour": 20,
    "Summary": "Shower",
    "Temperature": 19,
    "Feels like": 16,
    "Rain - 50%": 0,
    "Rain - 25%": 1,
    "Rain - 10%": 2,
    "Humidity": 65,
    "UV Index": 0,
    "Cloud cover": 71
  },
  {
    "Date": "2025-11-07",
    "Hour": 21,
    "Summary": "Shower",
    "Temperature": 18,
    "Feels like": 15,
    "Rain - 50%": 0,
    "Rain - 25%": 1,
    "Rain - 10%": 2,
    "Humidity": 72,
    "UV Index": 0,
    "Cloud cover": 71
  },
  {
    "Date": "2025-11-07",
    "Hour": 22,
    "Summary": "Shower",
    "Temperature": 16,
    "Feels like": 14,
    "Rain - 50%": 0,
    "Rain - 25%": 1,
    "Rain - 10%": 2,
    "Humidity": 78,
    "UV Index": 0,
    "Cloud cover": 71
  },
  {
    "Date": "2025-11-07",
    "Hour": 23,
    "Summary": "Shower",
    "Temperature": 15,
    "Feels like": 13,
    "Rain - 50%": 0,
    "Rain - 25%": 0,
    "Rain - 10%": 1,
    "Humidity": 86,
    "UV Index": 0,
    "Cloud cover": 76
  }
]