[
  {
    "time":"2026-04-25 00:00:00+00:00",
    "temperature_2m":18.0295009613,
    "apparent_temperature":16.3104953766,
    "dew_point_2m":8.7795000076,
    "relative_humidity_2m":54.7330322266,
    "precipitation":0.0,
    "rain":0.0,
    "snowfall":0.0,
    "cloud_cover":99.0,
    "pressure_msl":1023.799987793,
    "surface_pressure":1021.2813110352,
    "wind_speed_10m":9.587428093,
    "wind_direction_10m":320.3321838379,
    "wind_gusts_10m":27.7199993134,
    "visibility":null,
    "uv_index":null,
    "sunshine_duration":3600.0,
    "city":"Hobart"
  },
  {
    "time":"2026-04-25 01:00:00+00:00",
    "temperature_2m":19.6295013428,
    "apparent_temperature":17.8388195038,
    "dew_point_2m":9.0794992447,
    "relative_humidity_2m":50.5399131775,
    "precipitation":0.0,
    "rain":0.0,
    "snowfall":0.0,
    "cloud_cover":96.0,
    "pressure_msl":1023.0999755859,
    "surface_pressure":1020.5967407227,
    "wind_speed_10m":10.6260986328,
    "wind_direction_10m":321.1885986328,
    "wind_gusts_10m":30.2399978638,
    "visibility":null,
    "uv_index":null,
    "sunshine_duration":3600.0,
    "city":"Hobart"
  },
  {
    "time":"2026-04-25 02:00:00+00:00",
    "temperature_2m":21.9295005798,
    "apparent_temperature":19.9566898346,
    "dew_point_2m":8.8794994354,
    "relative_humidity_2m":43.2812042236,
    "precipitation":0.0,
    "rain":0.0,
    "snowfall":0.0,
    "cloud_cover":100.0,
    "pressure_msl":1022.0999755859,
    "surface_pressure":1019.6187133789,
    "wind_speed_10m":11.500295639,
    "wind_direction_10m":320.0796508789,
    "wind_gusts_10m":32.0399971008,
    "visibility":null,
    "uv_index":null,
    "sunshine_duration":3600.0,
    "city":"Hobart"
  },
  {
    "time":"2026-04-25 03:00:00+00:00",
    "temperature_2m":22.7795009613,
    "apparent_temperature":20.3608913422,
    "dew_point_2m":8.5295000076,
    "relative_humidity_2m":40.1397628784,
    "precipitation":0.0,
    "rain":0.0,
    "snowfall":0.0,
    "cloud_cover":98.0,
    "pressure_msl":1021.0999755859,
    "surface_pressure":1018.6281738281,
    "wind_speed_10m":13.9206466675,
    "wind_direction_10m":310.2797851562,
    "wind_gusts_10m":35.6399993896,
    "visibility":null,
    "uv_index":null,
    "sunshine_duration":3600.0,
    "city":"Hobart"
  },
  {
    "time":"2026-04-25 04:00:00+00:00",
    "temperature_2m":23.5795001984,
    "apparent_temperature":21.3087844849,
    "dew_point_2m":8.0795001984,
    "relative_humidity_2m":37.0957489014,
    "precipitation":0.0,
    "rain":0.0,
    "snowfall":0.0,
    "cloud_cover":99.0,
    "pressure_msl":1020.299987793,
    "surface_pressure":1017.836730957,
    "wind_speed_10m":12.1082611084,
    "wind_direction_10m":318.012878418,
    "wind_gusts_10m":35.6399993896,
    "visibility":null,
    "uv_index":null,
    "sunshine_duration":3600.0,
    "city":"Hobart"
  },
  {
    "time":"2026-04-25 05:00:00+00:00",
    "temperature_2m":23.5795001984,
    "apparent_temperature":21.2897071838,
    "dew_point_2m":7.8794999123,
    "relative_humidity_2m":36.5947952271,
    "precipitation":0.0,
    "rain":0.0,
    "snowfall":0.0,
    "cloud_cover":98.0,
    "pressure_msl":1019.700012207,
    "surface_pressure":1017.2382202148,
    "wind_speed_10m":11.8922653198,
    "wind_direction_10m":320.527557373,
    "wind_gusts_10m":30.9600009918,
    "visibility":null,
    "uv_index":null,
    "sunshine_duration":3600.0,
    "city":"Hobart"
  },
  {
    "time":"2026-04-25 06:00:00+00:00",
    "temperature_2m":23.3295001984,
    "apparent_temperature":21.7656002045,
    "dew_point_2m":9.0295000076,
    "relative_humidity_2m":40.1599121094,
    "precipitation":0.0,
    "rain":0.0,
    "snowfall":0.0,
    "cloud_cover":95.0,
    "pressure_msl":1019.5999755859,
    "surface_pressure":1017.1362304688,
    "wind_speed_10m":8.967540741,
    "wind_direction_10m":321.5197753906,
    "wind_gusts_10m":30.5999984741,
    "visibility":null,
    "uv_index":null,
    "sunshine_duration":3600.0,
    "city":"Hobart"
  },
  {
    "time":"2026-04-25 07:00:00+00:00",
    "temperature_2m":20.4295005798,
    "apparent_temperature":19.4240837097,
    "dew_point_2m":9.8294992447,
    "relative_humidity_2m":50.5841636658,
    "precipitation":0.0,
    "rain":0.0,
    "snowfall":0.0,
    "cloud_cover":100.0,
    "pressure_msl":1019.700012207,
    "surface_pressure":1017.2118530273,
    "wind_speed_10m":6.6599998474,
    "wind_direction_10m":341.0752563477,
    "wind_gusts_10m":22.6800003052,
    "visibility":null,
    "uv_index":null,
    "sunshine_duration":3600.0,
    "city":"Hobart"
  },
  {
    "time":"2026-04-25 08:00:00+00:00",
    "temperature_2m":18.3295001984,
    "apparent_temperature":17.1343860626,
    "dew_point_2m":9.1294994354,
    "relative_humidity_2m":54.9951210022,
    "precipitation":0.0,
    "rain":0.0,
    "snowfall":0.0,
    "cloud_cover":98.0,
    "pressure_msl":1019.700012207,
    "surface_pressure":1017.1939697266,
    "wind_speed_10m":6.6380720139,
    "wind_direction_10m":319.3987731934,
    "wind_gusts_10m":19.0799999237,
    "visibility":null,
    "uv_index":null,
    "sunshine_duration":0.0,
    "city":"Hobart"
  },
  {
    "time":"2026-04-25 09:00:00+00:00",
    "temperature_2m":16.9295005798,
    "apparent_temperature":15.6779842377,
    "dew_point_2m":9.0295000076,
    "relative_humidity_2m":59.6660995483,
    "precipitation":0.0,
    "rain":0.0,
    "snowfall":0.0,
    "cloud_cover":98.0,
    "pressure_msl":1019.799987793,
    "surface_pressure":1017.2816162109,
    "wind_speed_10m":6.8423676491,
    "wind_direction_10m":305.3625488281,
    "wind_gusts_10m":19.4400005341,
    "visibility":null,
    "uv_index":null,
    "sunshine_duration":0.0,
    "city":"Hobart"
  },
  {
    "time":"2026-04-25 10:00:00+00:00",
    "temperature_2m":15.5794992447,
    "apparent_temperature":14.1539802551,
    "dew_point_2m":9.0295000076,
    "relative_humidity_2m":65.0252609253,
    "precipitation":0.0,
    "rain":0.0,
    "snowfall":0.0,
    "cloud_cover":99.0,
    "pressure_msl":1019.799987793,
    "surface_pressure":1017.2697143555,
    "wind_speed_10m":8.0377607346,
    "wind_direction_10m":304.0459899902,
    "wind_gusts_10m":22.6800003052,
    "visibility":null,
    "uv_index":null,
    "sunshine_duration":0.0,
    "city":"Hobart"
  },
  {
    "time":"2026-04-25 11:00:00+00:00",
    "temperature_2m":15.0794992447,
    "apparent_temperature":13.543094635,
    "dew_point_2m":9.0794992447,
    "relative_humidity_2m":67.3720626831,
    "precipitation":0.0,
    "rain":0.0,
    "snowfall":0.0,
    "cloud_cover":100.0,
    "pressure_msl":1020.0,
    "surface_pressure":1017.4647827148,
    "wind_speed_10m":8.8913440704,
    "wind_direction_10m":291.3706970215,
    "wind_gusts_10m":24.4799995422,
    "visibility":null,
    "uv_index":null,
    "sunshine_duration":0.0,
    "city":"Hobart"
  },
  {
    "time":"2026-04-25 12:00:00+00:00",
    "temperature_2m":14.3794994354,
    "apparent_temperature":12.9509792328,
    "dew_point_2m":9.0295000076,
    "relative_humidity_2m":70.2449188232,
    "precipitation":0.0,
    "rain":0.0,
    "snowfall":0.0,
    "cloud_cover":100.0,
    "pressure_msl":1020.0999755859,
    "surface_pressure":1017.5584716797,
    "wind_speed_10m":8.0599002838,
    "wind_direction_10m":293.7026367188,
    "wind_gusts_10m":25.1999988556,
    "visibility":null,
    "uv_index":null,
    "sunshine_duration":0.0,
    "city":"Hobart"
  },
  {
    "time":"2026-04-25 13:00:00+00:00",
    "temperature_2m":14.1294994354,
    "apparent_temperature":12.4290351868,
    "dew_point_2m":8.9794998169,
    "relative_humidity_2m":71.1501846313,
    "precipitation":0.0,
    "rain":0.0,
    "snowfall":0.0,
    "cloud_cover":100.0,
    "pressure_msl":1019.9000244141,
    "surface_pressure":1017.3568115234,
    "wind_speed_10m":9.8326797485,
    "wind_direction_10m":293.7495117188,
    "wind_gusts_10m":28.7999992371,
    "visibility":null,
    "uv_index":null,
    "sunshine_duration":0.0,
    "city":"Hobart"
  },
  {
    "time":"2026-04-25 14:00:00+00:00",
    "temperature_2m":14.5794992447,
    "apparent_temperature":12.8908920288,
    "dew_point_2m":9.1294994354,
    "relative_humidity_2m":69.8121643066,
    "precipitation":0.0,
    "rain":0.0,
    "snowfall":0.0,
    "cloud_cover":99.0,
    "pressure_msl":1019.700012207,
    "surface_pressure":1017.1614379883,
    "wind_speed_10m":10.0284385681,
    "wind_direction_10m":291.0375671387,
    "wind_gusts_10m":29.1599998474,
    "visibility":null,
    "uv_index":null,
    "sunshine_duration":0.0,
    "city":"Hobart"
  },
  {
    "time":"2026-04-25 15:00:00+00:00",
    "temperature_2m":14.1294994354,
    "apparent_temperature":12.3549194336,
    "dew_point_2m":8.9294996262,
    "relative_humidity_2m":70.9106140137,
    "precipitation":0.0,
    "rain":0.0,
    "snowfall":0.0,
    "cloud_cover":100.0,
    "pressure_msl":1019.4000244141,
    "surface_pressure":1016.8580932617,
    "wind_speed_10m":10.2489414215,
    "wind_direction_10m":300.6185302734,
    "wind_gusts_10m":29.1599998474,
    "visibility":null,
    "uv_index":null,
    "sunshine_duration":0.0,
    "city":"Hobart"
  },
  {
    "time":"2026-04-25 16:00:00+00:00",
    "temperature_2m":14.3294992447,
    "apparent_temperature":12.5421066284,
    "dew_point_2m":8.7795000076,
    "relative_humidity_2m":69.2934265137,
    "precipitation":0.0,
    "rain":0.0,
    "snowfall":0.0,
    "cloud_cover":100.0,
    "pressure_msl":1019.200012207,
    "surface_pressure":1016.6604614258,
    "wind_speed_10m":10.0623054504,
    "wind_direction_10m":296.5649719238,
    "wind_gusts_10m":29.1599998474,
    "visibility":null,
    "uv_index":null,
    "sunshine_duration":0.0,
    "city":"Hobart"
  },
  {
    "time":"2026-04-25 17:00:00+00:00",
    "temperature_2m":14.3294992447,
    "apparent_temperature":12.605638504,
    "dew_point_2m":8.6294994354,
    "relative_humidity_2m":68.5944290161,
    "precipitation":0.0,
    "rain":0.0,
    "snowfall":0.0,
    "cloud_cover":100.0,
    "pressure_msl":1018.700012207,
    "surface_pressure":1016.1617431641,
    "wind_speed_10m":9.3548059464,
    "wind_direction_10m":300.0182800293,
    "wind_gusts_10m":28.4400005341,
    "visibility":null,
    "uv_index":null,
    "sunshine_duration":0.0,
    "city":"Hobart"
  },
  {
    "time":"2026-04-25 18:00:00+00:00",
    "temperature_2m":13.9294996262,
    "apparent_temperature":12.2532463074,
    "dew_point_2m":8.6294994354,
    "relative_humidity_2m":70.3947525024,
    "precipitation":0.0,
    "rain":0.0,
    "snowfall":0.0,
    "cloud_cover":99.0,
    "pressure_msl":1018.5,
    "surface_pressure":1015.9587402344,
    "wind_speed_10m":9.0287542343,
    "wind_direction_10m":293.4985656738,
    "wind_gusts_10m":26.2800006866,
    "visibility":null,
    "uv_index":null,
    "sunshine_duration":0.0,
    "city":"Hobart"
  },
  {
    "time":"2026-04-25 19:00:00+00:00",
    "temperature_2m":13.4294996262,
    "apparent_temperature":11.7577533722,
    "dew_point_2m":8.2795000076,
    "relative_humidity_2m":71.0165786743,
    "precipitation":0.0,
    "rain":0.0,
    "snowfall":0.0,
    "cloud_cover":100.0,
    "pressure_msl":1018.5,
    "surface_pressure":1015.9542236328,
    "wind_speed_10m":8.3733863831,
    "wind_direction_10m":295.4633178711,
    "wind_gusts_10m":25.1999988556,
    "visibility":null,
    "uv_index":null,
    "sunshine_duration":0.0,
    "city":"Hobart"
  },
  {
    "time":"2026-04-25 20:00:00+00:00",
    "temperature_2m":13.1794996262,
    "apparent_temperature":11.2562398911,
    "dew_point_2m":8.0295000076,
    "relative_humidity_2m":70.9686508179,
    "precipitation":0.0,
    "rain":0.0,
    "snowfall":0.0,
    "cloud_cover":100.0,
    "pressure_msl":1018.299987793,
    "surface_pressure":1015.7524414062,
    "wind_speed_10m":9.6598138809,
    "wind_direction_10m":296.5649719238,
    "wind_gusts_10m":26.6399993896,
    "visibility":null,
    "uv_index":null,
    "sunshine_duration":0.0,
    "city":"Hobart"
  },
  {
    "time":"2026-04-25 21:00:00+00:00",
    "temperature_2m":13.1794996262,
    "apparent_temperature":11.1711864471,
    "dew_point_2m":7.8794999123,
    "relative_humidity_2m":70.2484970093,
    "precipitation":0.0,
    "rain":0.0,
    "snowfall":0.0,
    "cloud_cover":100.0,
    "pressure_msl":1018.0999755859,
    "surface_pressure":1015.5529174805,
    "wind_speed_10m":9.9831056595,
    "wind_direction_10m":295.6409606934,
    "wind_gusts_10m":28.0799999237,
    "visibility":null,
    "uv_index":null,
    "sunshine_duration":0.0,
    "city":"Hobart"
  },
  {
    "time":"2026-04-25 22:00:00+00:00",
    "temperature_2m":14.1794996262,
    "apparent_temperature":12.2860202789,
    "dew_point_2m":8.3794994354,
    "relative_humidity_2m":68.1010437012,
    "precipitation":0.0,
    "rain":0.0,
    "snowfall":0.0,
    "cloud_cover":100.0,
    "pressure_msl":1018.299987793,
    "surface_pressure":1015.7613525391,
    "wind_speed_10m":10.0703525543,
    "wind_direction_10m":298.8555603027,
    "wind_gusts_10m":28.4400005341,
    "visibility":null,
    "uv_index":null,
    "sunshine_duration":0.0,
    "city":"Hobart"
  },
  {
    "time":"2026-04-25 23:00:00+00:00",
    "temperature_2m":16.3794994354,
    "apparent_temperature":14.83710289,
    "dew_point_2m":9.7294998169,
    "relative_humidity_2m":64.7645721436,
    "precipitation":0.0,
    "rain":0.0,
    "snowfall":0.0,
    "cloud_cover":98.0,
    "pressure_msl":1017.9000244141,
    "surface_pressure":1015.3814697266,
    "wind_speed_10m":10.1584444046,
    "wind_direction_10m":299.7447814941,
    "wind_gusts_10m":28.7999992371,
    "visibility":null,
    "uv_index":null,
    "sunshine_duration":3600.0,
    "city":"Hobart"
  }
]